__init__.py
profiling_helpers/__init__.py
profiling_helpers/profiling.py
profiling_helpers/save_targets.py
profiling_helpers-0.2.0.dist-info/LICENSE
profiling_helpers-0.2.0.dist-info/METADATA
profiling_helpers-0.2.0.dist-info/WHEEL
profiling_helpers-0.2.0.dist-info/top_level.txt
profiling_helpers-0.2.0.dist-info/RECORD
