Metadata-Version: 2.1
Name: profiling-helpers
Version: 0.2.0
Summary: A small utility library that wraps cProfile and makes it easy to debug performance problems in your Python code.
Home-page: https://github.com/NobisIndustries/python-profiling-helpers
Author: Fabian Nobis
Author-email: fabiannobis@gmx.de
License: MIT
Project-URL: Bug Tracker, https://github.com/NobisIndustries/python-profiling-helpers/issues
Keywords: cProfile,profiling,performance
Platform: any
Classifier: Development Status :: 4 - Beta
Classifier: Intended Audience :: Developers
Classifier: License :: OSI Approved :: MIT License
Classifier: Operating System :: OS Independent
Classifier: Programming Language :: Python
Classifier: Topic :: Software Development :: Libraries :: Python Modules
Requires-Python: >=3.7
License-File: LICENSE
Requires-Dist: snakeviz (>=2.1.1)
Provides-Extra: aws
Requires-Dist: boto3 (>=1.28.0) ; extra == 'aws'
Provides-Extra: dev
Requires-Dist: pre-commit ; extra == 'dev'
Requires-Dist: build ; extra == 'dev'
Requires-Dist: pytest ; extra == 'dev'
